ovp/__init__.py
ovp/package_data.dat
ovp-0.0.1.data/data/my_data/data_file
ovp-0.0.1.dist-info/LICENSE.txt
ovp-0.0.1.dist-info/METADATA
ovp-0.0.1.dist-info/WHEEL
ovp-0.0.1.dist-info/entry_points.txt
ovp-0.0.1.dist-info/top_level.txt
ovp-0.0.1.dist-info/RECORD
