Metadata-Version: 2.1
Name: ovp
Version: 0.0.1
Summary: Identity and Reputation
Home-page: https://github.com/shogoorg/pyovp
Author: Shogo
Author-email: shogo@example.com
License: UNKNOWN
Project-URL: Bug Reports, https://github.com/shogoorg/pyovp/issues
Project-URL: Source, https://github.com/shogoorg/pyovp/
Keywords: identity reputation ethereum ipfs networkx
Platform: UNKNOWN
Classifier: Development Status :: 3 - Alpha
Classifier: Intended Audience :: Developers
Classifier: Topic :: Software Development
Classifier: License :: OSI Approved :: MIT License
Classifier: Programming Language :: Python :: 3
Classifier: Programming Language :: Python :: 3.6
Requires-Python: >=3.6
Requires-Dist: vyper (==0.1.0b9)
Requires-Dist: ipfsapi (==0.4.3)
Requires-Dist: networkx (==2.2)
Provides-Extra: dev
Requires-Dist: check-manifest ; extra == 'dev'
Provides-Extra: test
Requires-Dist: coverage ; extra == 'test'
